pyo3_utils/__init__.py
pyo3_utils/py.typed
pyo3_utils-0.1.0b1.dist-info/METADATA
pyo3_utils-0.1.0b1.dist-info/WHEEL
pyo3_utils-0.1.0b1.dist-info/RECORD
