Metadata-Version: 2.4
Name: pyo3-utils
Version: 0.1.0b1
Summary: Python integration for the pyo3-utils crate.
Project-URL: documentation, https://wsh032.github.io/pytauri/
Project-URL: source, https://github.com/WSH032/pytauri
Author-email: Sean Wang <126865849+WSH032@users.noreply.github.com>
License-Expression: Apache-2.0
Requires-Python: >=3.9
Requires-Dist: typing-extensions>=4
